{
  "workspace_mode": "docker_mount",
  "workspace_container_root": "/workspace",
  "workspace_root": "/workspace/Projects",
  "workspace_host_root_hint": "C:\\AtlasWorkspace",
  "allow_project_atlas_folder": false,
  "auto_discover": true,
  "auto_index_on_scan": false,
  "last_scan_at": null,
  "excluded_dirs": [
    "node_modules",
    ".git",
    "dist",
    "build",
    ".next",
    ".venv",
    "venv",
    "__pycache__",
    ".expo",
    ".turbo",
    ".cache"
  ],
  "excluded_files": [
    ".env",
    ".env.local",
    ".env.production",
    "*.pem",
    "*.key",
    "*.sqlite",
    "*.db"
  ],
  "max_files_per_project": 8000,
  "max_file_size_mb": 2,
  "allowed_text_extensions": [
    ".md",
    ".txt",
    ".json",
    ".js",
    ".jsx",
    ".ts",
    ".tsx",
    ".py",
    ".html",
    ".css",
    ".scss",
    ".sql",
    ".yaml",
    ".yml",
    ".toml",
    ".dart"
  ]
}
